behave_classy
