Metadata-Version: 1.0
Name: behave-classy
Version: 1.0.0
Summary: Class-based step implementations for behave
Home-page: https://github.com/spyoungtech/behave-classy
Author: Spencer Young
Author-email: spencer.young@spyoung.com
License: MIT
Platform: UNKNOWN
